<step title="Incoming Request" date="2025-12-20T20:19:39.715" instance="93ba60" url="/api/deployments/latest?deployer=OneDeploy&amp;time=2025-12-20_20-19-12Z" method="GET" type="request" pid="837,1,21" Host="svs-stock-api.scm.azurewebsites.net" User-Agent="GITHUBACTIONS_DeployWebAppToAzure_9c77270b4dc11c65de193eb13ad2e59e3b6f8f2f23b9c7b3dc72a9e29892decc" Authorization="Bea..." Content-Type="application/json; charset=utf-8" Cookie="ARRAffinity=93ba60693efd27c98d25ac695a6ef440c44ba4652104de2a3ed78f5e62ba7f13;Path=/;HttpOnly;Secure;Domain=svs-stock-api.scm.azurewebsites.net; ARRAffinitySameSite=93ba60693efd27c98d25ac695a6ef440c44ba4652104de2a3ed78f5e62ba7f13;Path=/;HttpOnly;SameSite=None;Secure;Domain=svs-stock-api.scm.azurewebsites.net" Content-Length="0" X-ARR-LOG-ID="fa6a3912-3690-4b64-97f5-ce4183685736" CLIENT-IP="64.236.161.24:46081" X-SITE-DEPLOYMENT-ID="svs-stock-api" WAS-DEFAULT-HOSTNAME="svs-stock-api.scm.azurewebsites.net" X-Forwarded-Proto="https" X-AppService-Proto="https" X-Forwarded-TlsVersion="1.3" X-WAWS-Unencoded-URL="/api/deployments/latest?deployer=OneDeploy&amp;time=2025-12-20_20-19-12Z" X-Client-IP="64.236.161.24" X-Client-Port="46081" >
  <step title="Cleanup Xml Logs" date="2025-12-20T20:19:39.744" >
    <step title="Cleanup Infos" date="2025-12-20T20:19:39.856" totalFiles="746" totalCleanup="586" /><!-- duration: 21ms -->
  </step><!-- duration: 151ms -->
  <step title="DeploymentService.GetResult" date="2025-12-20T20:19:39.942" >
    <step title="DeploymentService.GetLatestDeployment" date="2025-12-20T20:19:39.959" >
      <step title="DeploymentManager.GetResults" date="2025-12-20T20:19:39.970" /><!-- duration: 1220ms -->
    </step><!-- duration: 1300ms -->
  </step><!-- duration: 1338ms -->
  <step title="Outgoing response" date="2025-12-20T20:19:41.298" type="response" statusCode="202" statusText="Accepted" /><!-- duration: 20ms -->
</step><!-- duration: 1632ms -->
